config/ablation_study.yml
config/all_possible_ablations.yaml
config/base_v1.yml
config/base_v1_5.yml
config/base_v2.yml
config/compress_class_medium.yaml
config/knncell.yml
config/predict.yml
config/pretrain_large.yml
config/pretrain_medium.yml
config/pretrain_vlarge.yml
config/scgpt.yml
config/others/pretrain_MLM.yml
config/others/pretrain_denoise.yml
config/others/pretrain_mvc.yml
config/others/pretrain_onlydenoise.yml
config/others/pretrain_small_2000.yml
config/others/pretrain_small_all.yml
config/others/pretrain_small_noClass.yml
config/others/pretrain_small_onlyDNS.yml
config/others/pretrain_small_onlyMLM.yml
scprint2/VERSION
scprint2/__init__.py
scprint2/__main__.py
scprint2/base.py
scprint2/cli.py
scprint2/datasets.py
scprint2/model/__init__.py
scprint2/model/decoders.py
scprint2/model/encoders.py
scprint2/model/fsq.py
scprint2/model/loss.py
scprint2/model/model.py
scprint2/model/utils.py
scprint2/tasks/__init__.py
scprint2/tasks/cell_emb.py
scprint2/tasks/denoise.py
scprint2/tasks/finetune.py
scprint2/tasks/gene_emb.py
scprint2/tasks/generate.py
scprint2/tasks/grn.py
scprint2/tasks/impute.py
scprint2/tasks/tmfg.py
scprint2/tokenizers/__init__.py
scprint2/tokenizers/embedder.py
scprint2/tokenizers/protein_embedder.py
scprint2/trainer/__init__.py
scprint2/trainer/trainer.py
scprint2/utils/__init__.py
scprint2/utils/get_seq.py
scprint2/utils/graph_refinement.py
scprint2/utils/sinkhorn.py
scprint2/utils/utils.py
slurm/any_sub.sh
slurm/submit.sh
data/main/TFs.txt
scprint2-0.9.8.dist-info/METADATA
scprint2-0.9.8.dist-info/WHEEL
scprint2-0.9.8.dist-info/entry_points.txt
scprint2-0.9.8.dist-info/licenses/LICENSE
scprint2-0.9.8.dist-info/RECORD
